<Tab name="Votekicks" padding="4 4 4 4">
    <Box padding="12 6 6 6" width="content" height="content" name="Votelogger">
        <List width="165">
            <AutoVariable width="fill" target="votelogger.autovote.yes" label="Autovote yes"/>
            <AutoVariable width="fill" target="votelogger.autovote.no" label="Autovote no"/>
            <AutoVariable width="fill" target="votelogger.autovote.no.rage" label="Kick RAGE status"/>
            <AutoVariable width="fill" target="votelogger.leave-after-local-vote" label="Abandon on local vote"/>
            <AutoVariable width="fill" target="votelogger.requeue-on-kick" label="Requeue on kick" tooltip="I couldn't come up with a better name for this lol"/>
            <AutoVariable width="fill" target="cat-bot.votekicks" label="Random votekicks"/>
            <AutoVariable width="fill" target="cat-bot.votekicks.rage-only" label="Rage only votekicks"/>
            <AutoVariable width="fill" target="cat-bot.votekicks.pazer-only" label="Pazer only votekicks"/>
            <AutoVariable width="fill" target="cat-bot.votekicks.abuse-only" label="Abuse only votekicks"/>
            <AutoVariable width="fill" target="cat-bot.votekicks.cheater-only" label="Cheater only votekicks"/>
        </List>
    </Box>
</Tab>
